[{"address":"Jl Margonda","size":2,"name":"Hotel Melati","facility":"AC","price":{"price":2000.0,"discount":0.0},"city":"DEPOK","booked":["Dec 1, 2022, 12:00:00 AM","Dec 2, 2022, 12:00:00 AM","Dec 3, 2022, 12:00:00 AM","Dec 8, 2022, 12:00:00 AM"],"accountId":0,"id":0},{"address":"Jl Margonda","size":2,"name":"Hotel Melati","facility":"AC","price":{"price":2000.0,"discount":0.0},"city":"DEPOK","booked":[],"accountId":0,"id":1},{"address":"Jl Margonda","size":2,"name":"Hotel Melati","facility":"AC","price":{"price":2000.0,"discount":0.0},"city":"DEPOK","booked":[],"accountId":0,"id":1},{"address":"Jl Margonda","size":2,"name":"Hotel Melati","facility":"AC","price":{"price":2000.0,"discount":0.0},"city":"DEPOK","booked":[],"accountId":0,"id":2},{"address":"Jl Margonda","size":2,"name":"Hotel Melati","facility":"AC","price":{"price":2000.0,"discount":0.0},"city":"DEPOK","booked":[],"accountId":0,"id":3}]